CheckerService/__init__.py
CheckerService/__main__.py
CheckerService/api.py
CheckerService/const.py
CheckerService/service.py
pih_check-0.17.dist-info/METADATA
pih_check-0.17.dist-info/WHEEL
pih_check-0.17.dist-info/entry_points.txt
pih_check-0.17.dist-info/top_level.txt
pih_check-0.17.dist-info/RECORD
