Metadata-Version: 2.1
Name: pih-check
Version: 0.17
Summary: PIH Checker service package
Home-page: https://pacifichosp.com/
Author: Nikita Karachentsev
Author-email: it@pacifichosp.com
License: MIT
Requires-Dist: ipih
